<?xml version="1.0" encoding="utf-8" ?><dwsync><file name=".DS_Store" server="ftp.260mb.net/htdocs/miperfil/" local="3543273324" remote="318763443936178452" Dst="-1" /><file name="favicon.ico" server="ftp.260mb.net/htdocs/miperfil/" local="3542840129" remote="318763443935746152" Dst="-1" /><file name="avatar.jpg" server="ftp.260mb.net/htdocs/miperfil/" local="3543273411" remote="318763443936178452" Dst="-1" /><file name="bg_header1.jpg" server="ftp.260mb.net/htdocs/miperfil/" local="3499096616" remote="318763443936178452" Dst="-1" /><file name="portada.jpg" server="ftp.260mb.net/htdocs/miperfil/" local="3499096616" remote="318763443936178452" Dst="-1" /><file name="footer.jpg" server="ftp.260mb.net/htdocs/miperfil/" local="3499096616" remote="318763443936178452" Dst="-1" /><file name="proyecto.jpg" server="ftp.260mb.net/htdocs/miperfil/" local="3499096616" remote="318763443936178452" Dst="-1" /><file name="thumb2.jpg" server="ftp.260mb.net/htdocs/miperfil/" local="3499096616" remote="318763443936178452" Dst="-1" /><file name="thumb3.jpg" server="ftp.260mb.net/htdocs/miperfil/" local="3499096616" remote="318763443936178452" Dst="-1" /><file name="Home.png" server="ftp.260mb.net/htdocs/miperfil/" local="3528832692" remote="318763443936178452" Dst="-1" /></dwsync>